pipver/__init__.py
pipver/lib.py
pipver/semanticversion.py
pipver-0.1.10.dist-info/entry_points.txt
pipver-0.1.10.dist-info/LICENSE
pipver-0.1.10.dist-info/WHEEL
pipver-0.1.10.dist-info/METADATA
pipver-0.1.10.dist-info/RECORD
